pgcolpos/__init__.py
pgcolpos/cli.py
pgcolpos/main.py
pgcolpos-1.0.0.dist-info/licenses/LICENSE
tests/__init__.py
tests/test_pgcolpos.py
pgcolpos-1.0.0.dist-info/METADATA
pgcolpos-1.0.0.dist-info/WHEEL
pgcolpos-1.0.0.dist-info/top_level.txt
pgcolpos-1.0.0.dist-info/RECORD
