Metadata-Version: 2.4
Name: pgcolpos
Version: 1.0.0
Summary: A tool to add or move columns to specific positions in PostgreSQL tables
Home-page: https://github.com/lmousom/pgcolpos
Author: Latiful Mousom
Author-email: Latiful Mousom <latifulmousom@gmail.com>
License: MIT
Classifier: Programming Language :: Python :: 3
Classifier: Programming Language :: Python :: 3.8
Classifier: Programming Language :: Python :: 3.9
Classifier: Programming Language :: Python :: 3.10
Classifier: Programming Language :: Python :: 3.11
Classifier: License :: OSI Approved :: MIT License
Classifier: Operating System :: OS Independent
Requires-Python: >=3.8
License-File: LICENSE
Dynamic: author
Dynamic: home-page
Dynamic: license-file
Dynamic: requires-python
